{
    "brand": "GUCCI",
    "brand_essence": {
      "core_identity": "Eclectic, contemporary, romantic",
      "heritage": "Founded in Florence in 1921, Gucci represents the pinnacle of Italian craftsmanship and elegance",
      "brand_voice": "Bold, sophisticated, inclusive yet exclusive"
    },
    "aesthetic_pillars": {
      "visual_language": [
        "Maximalist luxury",
        "Contemporary eclecticism",
        "Romantic heritage",
        "Artistic irreverence",
        "Renaissance meets street culture"
      ],
      "emotional_attributes": [
        "Empowered",
        "Sophisticated",
        "Daring",
        "Self-expressive",
        "Culturally fluid"
      ],
      "signature_elements": [
        "Blend of historical elements with contemporary culture",
        "Subversive romanticism",
        "Luxurious disruption",
        "Gender fluid expression",
        "Bold pattern mixing"
      ]
    },
    "cultural_positioning": {
      "philosophy": "Progressive, inclusive and sustainable luxury that drives a positive change",
      "core_values": [
        "Creative freedom",
        "Respect for heritage",
        "Sustainable innovation",
        "Inclusivity within exclusivity",
        "Artistic collaboration"
      ],
      "cultural_codes": [
        "High art meets street culture",
        "Digital innovation with artisanal tradition",
        "Sustainable luxury",
        "Cultural fluidity",
        "Generational inclusivity"
      ]
    },
    "target_mindset": {
      "aspirations": [
        "Cultural leadership",
        "Creative self-expression",
        "Sophisticated rebellion",
        "Social recognition",
        "Artistic appreciation"
      ],
      "lifestyle_attributes": [
        "Culturally engaged",
        "Digitally native",
        "Globally minded",
        "Style-conscious",
        "Experience-seeking"
      ]
    },
    "brand_expressions": {
      "tone": [
        "Bold yet refined",
        "Intellectually playful",
        "Culturally informed",
        "Artistically provocative",
        "Confidently eccentric"
      ],
      "experience": [
        "Immersive luxury",
        "Digital innovation",
        "Artistic dialogue",
        "Cultural storytelling",
        "Sustainable consciousness"
      ]
    }
  }